flask_redis_sentinel.py
Flask_Redis_Sentinel-2.0.1.dist-info/DESCRIPTION.rst
Flask_Redis_Sentinel-2.0.1.dist-info/METADATA
Flask_Redis_Sentinel-2.0.1.dist-info/RECORD
Flask_Redis_Sentinel-2.0.1.dist-info/WHEEL
Flask_Redis_Sentinel-2.0.1.dist-info/metadata.json
Flask_Redis_Sentinel-2.0.1.dist-info/top_level.txt
