Metadata-Version: 2.0
Name: Flask-Redis-Sentinel
Version: 2.0.1
Summary: Redis-Sentinel integration for Flask
Home-page: https://github.com/exponea/flask-redis-sentinel
Author: Martin Sucha
Author-email: martin.sucha@exponea.com
License: Apache 2.0
Platform: UNKNOWN
Classifier: Programming Language :: Python
Classifier: Programming Language :: Python :: 2
Classifier: Programming Language :: Python :: 2.7
Classifier: Programming Language :: Python :: 3
Classifier: Programming Language :: Python :: 3.3
Classifier: Programming Language :: Python :: 3.4
Classifier: Programming Language :: Python :: 3.5
Classifier: Programming Language :: Python :: 3.6
Classifier: Operating System :: OS Independent
Classifier: License :: OSI Approved :: Apache Software License
Classifier: Development Status :: 5 - Production/Stable
Classifier: Intended Audience :: Developers
Classifier: Topic :: Software Development :: Libraries :: Python Modules
Requires-Dist: Flask (>=0.10.1)
Requires-Dist: redis (>=2.10.3)
Requires-Dist: redis-sentinel-url (>=1.0.0,<2.0.0)
Requires-Dist: six
